dstack_tasks/__init__.py
dstack_tasks/base.py
dstack_tasks/develop.py
dstack_tasks/factory.py
dstack_tasks/main.py
dstack_tasks/notify.py
dstack_tasks/remote.py
dstack_tasks/server.py
dstack_tasks/tasks.py
dstack_tasks/utils.py
dstack_tasks/wrap.py
dstack_tasks-2.3.5.dist-info/METADATA
dstack_tasks-2.3.5.dist-info/WHEEL
dstack_tasks-2.3.5.dist-info/entry_points.txt
dstack_tasks-2.3.5.dist-info/top_level.txt
dstack_tasks-2.3.5.dist-info/zip-safe
dstack_tasks-2.3.5.dist-info/RECORD
