Metadata-Version: 2.1
Name: dstack-tasks
Version: 2.3.5
Summary: CLI that accompanies dstack-tasks make it easy to build and deploy application. Integrates with dstack-factory.
Home-page: https://github.com/obitec/dstack-tasks
Author: J Minnaar
Author-email: jr.minnaar@gmail.com
License: MIT License
Keywords: docker python wheels images runtime automation deploy
Platform: UNKNOWN
Classifier: Development Status :: 5 - Production/Stable
Classifier: Intended Audience :: System Administrators
Classifier: Topic :: Software Development :: Build Tools
Classifier: Topic :: System :: Installation/Setup
Classifier: Topic :: System :: Software Distribution
Classifier: Operating System :: OS Independent
Classifier: License :: OSI Approved :: MIT License
Classifier: Programming Language :: Python
Classifier: Programming Language :: Python :: 3
Classifier: Programming Language :: Python :: 3.7
Classifier: Programming Language :: Python :: 3.8
Requires-Dist: awscli
Requires-Dist: boto3
Requires-Dist: colorama
Requires-Dist: fabric
Requires-Dist: invoke
Requires-Dist: python-dotenv
Requires-Dist: requests
Provides-Extra: dev
Requires-Dist: twine ; extra == 'dev'
Requires-Dist: wheel ; extra == 'dev'
